{"name":"Bridger","gender":"M","years":{"1974":{"count":5,"rank":5299},"1977":{"count":10,"rank":3635},"1978":{"count":14,"rank":2950},"1979":{"count":11,"rank":3591},"1980":{"count":10,"rank":3881},"1981":{"count":15,"rank":2914},"1982":{"count":12,"rank":3510},"1983":{"count":16,"rank":2802},"1984":{"count":15,"rank":2977},"1985":{"count":13,"rank":3427},"1986":{"count":19,"rank":2696},"1987":{"count":20,"rank":2644},"1988":{"count":15,"rank":3374},"1989":{"count":18,"rank":3218},"1990":{"count":32,"rank":2221},"1991":{"count":21,"rank":3003},"1992":{"count":41,"rank":1957},"1993":{"count":36,"rank":2167},"1994":{"count":58,"rank":1582},"1995":{"count":74,"rank":1370},"1996":{"count":93,"rank":1207},"1997":{"count":115,"rank":1099},"1998":{"count":108,"rank":1162},"1999":{"count":142,"rank":993},"2000":{"count":144,"rank":1015},"2001":{"count":153,"rank":997},"2002":{"count":149,"rank":1026},"2003":{"count":161,"rank":985},"2004":{"count":158,"rank":1035},"2005":{"count":168,"rank":1011},"2006":{"count":167,"rank":1072},"2007":{"count":181,"rank":1038},"2008":{"count":206,"rank":968},"2009":{"count":242,"rank":867},"2010":{"count":219,"rank":919},"2011":{"count":207,"rank":958},"2012":{"count":217,"rank":936},"2013":{"count":230,"rank":905},"2014":{"count":211,"rank":986},"2015":{"count":198,"rank":1023},"2016":{"count":263,"rank":856},"2017":{"count":221,"rank":944},"2018":{"count":229,"rank":926},"2019":{"count":242,"rank":908},"2020":{"count":239,"rank":931},"2021":{"count":357,"rank":723},"2022":{"count":348,"rank":739},"2023":{"count":348,"rank":750},"2024":{"count":319,"rank":785}}}