{"name":"Chelsei","gender":"F","years":{"1987":{"count":5,"rank":11623},"1988":{"count":7,"rank":9450},"1989":{"count":12,"rank":6617},"1990":{"count":12,"rank":6951},"1991":{"count":13,"rank":6670},"1992":{"count":23,"rank":4399},"1993":{"count":11,"rank":7597},"1994":{"count":6,"rank":12081},"1995":{"count":16,"rank":5727},"1996":{"count":15,"rank":6119},"1997":{"count":8,"rank":9982},"1998":{"count":6,"rank":12775},"2000":{"count":6,"rank":13512},"2005":{"count":5,"rank":17027},"2006":{"count":6,"rank":15534},"2007":{"count":5,"rank":18201},"2013":{"count":5,"rank":17107}}}