{"name":"Damiya","gender":"F","years":{"1997":{"count":10,"rank":8508},"1998":{"count":8,"rank":10336},"1999":{"count":12,"rank":7840},"2000":{"count":21,"rank":5354},"2001":{"count":17,"rank":6391},"2002":{"count":16,"rank":6781},"2003":{"count":28,"rank":4573},"2004":{"count":31,"rank":4417},"2005":{"count":38,"rank":3821},"2006":{"count":52,"rank":3185},"2007":{"count":46,"rank":3545},"2008":{"count":55,"rank":3087},"2009":{"count":48,"rank":3424},"2010":{"count":59,"rank":2913},"2011":{"count":44,"rank":3559},"2012":{"count":49,"rank":3327},"2013":{"count":56,"rank":2982},"2014":{"count":43,"rank":3602},"2015":{"count":40,"rank":3786},"2016":{"count":25,"rank":5321},"2017":{"count":39,"rank":3861},"2018":{"count":38,"rank":3868},"2019":{"count":28,"rank":4797},"2020":{"count":21,"rank":5702},"2021":{"count":22,"rank":5606},"2022":{"count":27,"rank":4931},"2023":{"count":16,"rank":6999},"2024":{"count":12,"rank":8541}}}