{"name":"Desaree","gender":"F","years":{"1921":{"count":5,"rank":5302},"1955":{"count":5,"rank":6053},"1962":{"count":6,"rank":6032},"1964":{"count":6,"rank":6185},"1965":{"count":5,"rank":6764},"1967":{"count":5,"rank":7036},"1968":{"count":5,"rank":7269},"1969":{"count":11,"rank":4499},"1971":{"count":5,"rank":8651},"1972":{"count":6,"rank":7509},"1973":{"count":11,"rank":4959},"1975":{"count":6,"rank":8242},"1976":{"count":7,"rank":7485},"1977":{"count":6,"rank":8721},"1978":{"count":9,"rank":6523},"1979":{"count":13,"rank":5166},"1980":{"count":13,"rank":5311},"1981":{"count":9,"rank":6934},"1982":{"count":17,"rank":4388},"1983":{"count":14,"rank":4941},"1984":{"count":21,"rank":3760},"1985":{"count":14,"rank":5134},"1986":{"count":10,"rank":6725},"1987":{"count":25,"rank":3544},"1988":{"count":26,"rank":3609},"1989":{"count":27,"rank":3700},"1990":{"count":34,"rank":3239},"1991":{"count":24,"rank":4237},"1992":{"count":22,"rank":4578},"1993":{"count":26,"rank":4015},"1994":{"count":28,"rank":3814},"1995":{"count":34,"rank":3300},"1996":{"count":32,"rank":3524},"1997":{"count":15,"rank":6251},"1998":{"count":21,"rank":5002},"1999":{"count":14,"rank":6922},"2000":{"count":16,"rank":6575},"2001":{"count":17,"rank":6404},"2002":{"count":18,"rank":6212},"2003":{"count":11,"rank":9210},"2004":{"count":16,"rank":7172},"2005":{"count":11,"rank":9621},"2006":{"count":11,"rank":10085},"2007":{"count":9,"rank":11895},"2008":{"count":10,"rank":11017},"2009":{"count":8,"rank":12744},"2010":{"count":7,"rank":13863},"2012":{"count":7,"rank":13872}}}