{"name":"Dionis","gender":"M","years":{"1983":{"count":6,"rank":5668},"1987":{"count":8,"rank":5090},"1990":{"count":6,"rank":7417},"1991":{"count":5,"rank":8547},"1992":{"count":5,"rank":8776},"1996":{"count":5,"rank":9381},"1998":{"count":5,"rank":10044},"1999":{"count":5,"rank":10342},"2002":{"count":6,"rank":9696},"2004":{"count":9,"rank":7697},"2005":{"count":8,"rank":8494},"2007":{"count":8,"rank":9118},"2009":{"count":7,"rank":10134},"2012":{"count":7,"rank":9985},"2013":{"count":5,"rank":12623},"2017":{"count":7,"rank":9952},"2019":{"count":5,"rank":12647},"2020":{"count":5,"rank":12525},"2022":{"count":5,"rank":12824}}}