{"name":"Glynnis","gender":"F","years":{"1951":{"count":7,"rank":4539},"1953":{"count":7,"rank":4747},"1954":{"count":11,"rank":3572},"1955":{"count":16,"rank":2880},"1956":{"count":8,"rank":4591},"1957":{"count":14,"rank":3198},"1958":{"count":13,"rank":3433},"1959":{"count":5,"rank":6593},"1960":{"count":8,"rank":4918},"1961":{"count":12,"rank":3853},"1962":{"count":16,"rank":3211},"1963":{"count":39,"rank":1875},"1964":{"count":40,"rank":1873},"1965":{"count":25,"rank":2427},"1966":{"count":17,"rank":3086},"1967":{"count":12,"rank":3915},"1968":{"count":16,"rank":3373},"1969":{"count":12,"rank":4271},"1970":{"count":11,"rank":4854},"1971":{"count":9,"rank":5689},"1972":{"count":7,"rank":6786},"1973":{"count":9,"rank":5718},"1974":{"count":13,"rank":4546},"1975":{"count":6,"rank":8339},"1977":{"count":6,"rank":8809},"1978":{"count":10,"rank":6095},"1979":{"count":9,"rank":6893},"1980":{"count":13,"rank":5331},"1981":{"count":9,"rank":6985},"1983":{"count":10,"rank":6383},"1984":{"count":10,"rank":6452},"1985":{"count":15,"rank":4925},"1986":{"count":12,"rank":5885},"1987":{"count":13,"rank":5703},"1988":{"count":15,"rank":5413},"1989":{"count":8,"rank":9022},"1990":{"count":13,"rank":6596},"1991":{"count":6,"rank":12027},"1992":{"count":8,"rank":9796},"1993":{"count":7,"rank":10979},"1995":{"count":8,"rank":9892},"1996":{"count":9,"rank":9057},"1997":{"count":11,"rank":7960},"1998":{"count":10,"rank":8815},"1999":{"count":8,"rank":10688},"2000":{"count":6,"rank":13756},"2006":{"count":5,"rank":18111},"2008":{"count":5,"rank":18488}}}