{"name":"Halim","gender":"M","years":{"1975":{"count":5,"rank":5787},"1976":{"count":5,"rank":5934},"1979":{"count":5,"rank":6418},"1980":{"count":5,"rank":6623},"1981":{"count":8,"rank":4685},"1982":{"count":6,"rank":5916},"1985":{"count":7,"rank":5366},"1987":{"count":6,"rank":6399},"1993":{"count":10,"rank":5500},"1995":{"count":5,"rank":9358},"1996":{"count":5,"rank":9531},"1997":{"count":10,"rank":5801},"2000":{"count":6,"rank":9521},"2001":{"count":10,"rank":6627},"2002":{"count":9,"rank":7245},"2005":{"count":9,"rank":7867},"2007":{"count":10,"rank":7793},"2008":{"count":10,"rank":7889},"2009":{"count":7,"rank":10228},"2010":{"count":6,"rank":11232},"2011":{"count":10,"rank":7691},"2012":{"count":6,"rank":11287},"2013":{"count":5,"rank":12803},"2014":{"count":8,"rank":9068},"2015":{"count":5,"rank":12752},"2016":{"count":12,"rank":6865},"2017":{"count":5,"rank":12947},"2020":{"count":7,"rank":9921},"2021":{"count":8,"rank":9132},"2022":{"count":8,"rank":9290},"2023":{"count":10,"rank":7908},"2024":{"count":8,"rank":9273}}}