{"name":"Hector","gender":"F","years":{"1935":{"count":5,"rank":4490},"1951":{"count":5,"rank":5724},"1954":{"count":5,"rank":6069},"1957":{"count":5,"rank":6436},"1959":{"count":7,"rank":5230},"1961":{"count":6,"rank":6094},"1962":{"count":7,"rank":5493},"1963":{"count":10,"rank":4364},"1964":{"count":8,"rank":5172},"1965":{"count":7,"rank":5477},"1967":{"count":7,"rank":5667},"1968":{"count":9,"rank":4897},"1969":{"count":6,"rank":6934},"1970":{"count":11,"rank":4861},"1971":{"count":9,"rank":5695},"1972":{"count":14,"rank":4160},"1973":{"count":8,"rank":6283},"1974":{"count":18,"rank":3605},"1975":{"count":14,"rank":4428},"1976":{"count":11,"rank":5343},"1977":{"count":8,"rank":7109},"1978":{"count":14,"rank":4767},"1979":{"count":16,"rank":4484},"1980":{"count":21,"rank":3761},"1981":{"count":6,"rank":9494},"1982":{"count":13,"rank":5322},"1983":{"count":13,"rank":5243},"1984":{"count":16,"rank":4561},"1985":{"count":14,"rank":5157},"1986":{"count":18,"rank":4419},"1987":{"count":19,"rank":4356},"1988":{"count":18,"rank":4714},"1989":{"count":11,"rank":7143},"1990":{"count":12,"rank":7030},"1991":{"count":16,"rank":5760},"1992":{"count":13,"rank":6791},"1993":{"count":18,"rank":5290},"1994":{"count":18,"rank":5325},"1995":{"count":11,"rank":7706},"1996":{"count":12,"rank":7297},"1999":{"count":5,"rank":15266},"2001":{"count":5,"rank":16250},"2004":{"count":5,"rank":17072},"2008":{"count":7,"rank":14383}}}