{"name":"Janitza","gender":"F","years":{"1980":{"count":6,"rank":9545},"1981":{"count":6,"rank":9540},"1983":{"count":7,"rank":8372},"1984":{"count":5,"rank":11052},"1985":{"count":9,"rank":7188},"1986":{"count":8,"rank":8028},"1987":{"count":8,"rank":8294},"1988":{"count":7,"rank":9655},"1989":{"count":10,"rank":7656},"1990":{"count":8,"rank":9605},"1992":{"count":12,"rank":7214},"1993":{"count":5,"rank":14385},"1994":{"count":9,"rank":9122},"1995":{"count":6,"rank":12390},"1996":{"count":7,"rank":11033},"1998":{"count":9,"rank":9612},"1999":{"count":16,"rank":6310},"2001":{"count":6,"rank":14252},"2002":{"count":16,"rank":6845},"2003":{"count":12,"rank":8728},"2004":{"count":16,"rank":7218},"2005":{"count":17,"rank":6966},"2006":{"count":10,"rank":10938},"2007":{"count":11,"rank":10415},"2008":{"count":13,"rank":9185},"2009":{"count":11,"rank":10262},"2010":{"count":8,"rank":12787},"2011":{"count":9,"rank":11590},"2012":{"count":6,"rank":15767},"2013":{"count":6,"rank":15404},"2014":{"count":5,"rank":17644},"2016":{"count":7,"rank":13494},"2018":{"count":5,"rank":16676},"2021":{"count":9,"rank":10621}}}