{"name":"Jaun","gender":"M","years":{"1947":{"count":6,"rank":3535},"1948":{"count":5,"rank":3920},"1950":{"count":6,"rank":3492},"1951":{"count":5,"rank":3965},"1952":{"count":10,"rank":2600},"1956":{"count":7,"rank":3353},"1958":{"count":6,"rank":3715},"1960":{"count":11,"rank":2605},"1961":{"count":8,"rank":3214},"1962":{"count":5,"rank":4318},"1963":{"count":7,"rank":3467},"1964":{"count":5,"rank":4307},"1965":{"count":7,"rank":3388},"1967":{"count":8,"rank":3100},"1968":{"count":5,"rank":4402},"1969":{"count":11,"rank":2769},"1970":{"count":13,"rank":2675},"1971":{"count":8,"rank":3788},"1972":{"count":10,"rank":3241},"1973":{"count":6,"rank":4767},"1974":{"count":12,"rank":3028},"1975":{"count":14,"rank":2819},"1976":{"count":8,"rank":4188},"1977":{"count":14,"rank":2972},"1978":{"count":13,"rank":3135},"1979":{"count":12,"rank":3446},"1980":{"count":12,"rank":3497},"1981":{"count":17,"rank":2717},"1982":{"count":17,"rank":2759},"1983":{"count":10,"rank":3995},"1984":{"count":11,"rank":3802},"1985":{"count":13,"rank":3496},"1986":{"count":12,"rank":3735},"1987":{"count":8,"rank":5166},"1988":{"count":14,"rank":3597},"1989":{"count":22,"rank":2828},"1990":{"count":14,"rank":4072},"1991":{"count":11,"rank":4912},"1992":{"count":11,"rank":5036},"1993":{"count":20,"rank":3303},"1994":{"count":7,"rank":7300},"1995":{"count":8,"rank":6642},"1996":{"count":8,"rank":6759},"1997":{"count":9,"rank":6317},"1998":{"count":9,"rank":6527},"1999":{"count":16,"rank":4445},"2000":{"count":11,"rank":6091},"2002":{"count":10,"rank":6753},"2003":{"count":13,"rank":5695},"2004":{"count":6,"rank":10550},"2005":{"count":9,"rank":7936},"2006":{"count":8,"rank":9078},"2007":{"count":8,"rank":9269},"2009":{"count":5,"rank":13300},"2014":{"count":5,"rank":12902}}}