{"name":"Jennife","gender":"F","years":{"1965":{"count":8,"rank":5001},"1967":{"count":5,"rank":7210},"1969":{"count":8,"rank":5652},"1970":{"count":14,"rank":4123},"1971":{"count":12,"rank":4656},"1972":{"count":21,"rank":3109},"1973":{"count":14,"rank":4227},"1974":{"count":23,"rank":3039},"1975":{"count":14,"rank":4432},"1976":{"count":13,"rank":4731},"1977":{"count":7,"rank":7855},"1978":{"count":11,"rank":5695},"1979":{"count":9,"rank":6939},"1980":{"count":10,"rank":6487},"1981":{"count":13,"rank":5390},"1982":{"count":14,"rank":5042},"1983":{"count":8,"rank":7578},"1984":{"count":15,"rank":4828},"1985":{"count":11,"rank":6206},"1986":{"count":11,"rank":6337},"1987":{"count":15,"rank":5160},"1988":{"count":9,"rank":7971}}}