{"name":"Jung","gender":"M","years":{"1945":{"count":5,"rank":3547},"1967":{"count":7,"rank":3402},"1968":{"count":5,"rank":4426},"1970":{"count":6,"rank":4489},"1971":{"count":6,"rank":4664},"1973":{"count":5,"rank":5474},"1977":{"count":5,"rank":6331},"1979":{"count":7,"rank":5108},"1982":{"count":10,"rank":4089},"1983":{"count":8,"rank":4706},"1984":{"count":6,"rank":5966},"1986":{"count":10,"rank":4299},"1988":{"count":9,"rank":4998},"1989":{"count":8,"rank":5917},"1990":{"count":8,"rank":6124},"1991":{"count":7,"rank":6898},"1992":{"count":8,"rank":6392},"1994":{"count":7,"rank":7347},"1996":{"count":6,"rank":8438},"1997":{"count":5,"rank":10011},"1999":{"count":5,"rank":10740},"2000":{"count":5,"rank":11265},"2002":{"count":6,"rank":10014}}}