{"name":"Kemari","gender":"F","years":{"1991":{"count":5,"rank":14229},"1994":{"count":5,"rank":14533},"1996":{"count":6,"rank":12638},"1997":{"count":6,"rank":12911},"1998":{"count":8,"rank":10621},"1999":{"count":6,"rank":13524},"2000":{"count":11,"rank":8875},"2001":{"count":15,"rank":7140},"2002":{"count":7,"rank":12921},"2003":{"count":12,"rank":8786},"2004":{"count":15,"rank":7619},"2005":{"count":26,"rank":5036},"2006":{"count":23,"rank":5825},"2007":{"count":27,"rank":5310},"2008":{"count":24,"rank":5859},"2009":{"count":34,"rank":4422},"2010":{"count":27,"rank":5176},"2011":{"count":22,"rank":6042},"2012":{"count":23,"rank":5800},"2013":{"count":16,"rank":7578},"2014":{"count":26,"rank":5231},"2015":{"count":17,"rank":7124},"2016":{"count":21,"rank":6079},"2017":{"count":16,"rank":7254},"2018":{"count":16,"rank":7249},"2019":{"count":22,"rank":5708},"2020":{"count":15,"rank":7393},"2021":{"count":24,"rank":5318},"2022":{"count":23,"rank":5551},"2023":{"count":15,"rank":7452},"2024":{"count":9,"rank":10656}}}