{"name":"Kilian","gender":"M","years":{"1970":{"count":5,"rank":5107},"1972":{"count":6,"rank":4731},"1975":{"count":8,"rank":4135},"1976":{"count":6,"rank":5300},"1977":{"count":6,"rank":5516},"1978":{"count":6,"rank":5457},"1982":{"count":5,"rank":6906},"1984":{"count":6,"rank":5998},"1988":{"count":10,"rank":4618},"1989":{"count":12,"rank":4415},"1990":{"count":18,"rank":3395},"1991":{"count":16,"rank":3745},"1992":{"count":28,"rank":2577},"1993":{"count":20,"rank":3319},"1994":{"count":20,"rank":3407},"1995":{"count":25,"rank":2890},"1996":{"count":25,"rank":2981},"1997":{"count":20,"rank":3533},"1998":{"count":21,"rank":3557},"1999":{"count":25,"rank":3238},"2000":{"count":22,"rank":3711},"2001":{"count":32,"rank":2903},"2002":{"count":20,"rank":4129},"2003":{"count":21,"rank":4059},"2004":{"count":32,"rank":3120},"2005":{"count":26,"rank":3677},"2006":{"count":35,"rank":3127},"2007":{"count":36,"rank":3163},"2008":{"count":44,"rank":2772},"2009":{"count":47,"rank":2642},"2010":{"count":43,"rank":2810},"2011":{"count":40,"rank":2932},"2012":{"count":59,"rank":2225},"2013":{"count":41,"rank":2824},"2014":{"count":91,"rank":1686},"2015":{"count":132,"rank":1336},"2016":{"count":161,"rank":1180},"2017":{"count":162,"rank":1161},"2018":{"count":145,"rank":1273},"2019":{"count":132,"rank":1357},"2020":{"count":153,"rank":1227},"2021":{"count":168,"rank":1171},"2022":{"count":161,"rank":1222},"2023":{"count":212,"rank":1032},"2024":{"count":209,"rank":1050}}}