{"name":"Kiyoshi","gender":"M","years":{"1910":{"count":5,"rank":1731},"1912":{"count":9,"rank":1820},"1913":{"count":7,"rank":2386},"1914":{"count":17,"rank":1529},"1915":{"count":31,"rank":1173},"1916":{"count":39,"rank":1035},"1917":{"count":38,"rank":1087},"1918":{"count":42,"rank":1049},"1919":{"count":53,"rank":923},"1920":{"count":53,"rank":955},"1921":{"count":53,"rank":964},"1922":{"count":56,"rank":934},"1923":{"count":66,"rank":838},"1924":{"count":56,"rank":940},"1925":{"count":60,"rank":863},"1926":{"count":47,"rank":1014},"1927":{"count":38,"rank":1170},"1928":{"count":31,"rank":1313},"1929":{"count":18,"rank":1833},"1930":{"count":21,"rank":1629},"1931":{"count":18,"rank":1745},"1932":{"count":19,"rank":1689},"1933":{"count":18,"rank":1681},"1934":{"count":12,"rank":2187},"1935":{"count":10,"rank":2464},"1936":{"count":14,"rank":1930},"1937":{"count":7,"rank":3048},"1938":{"count":9,"rank":2565},"1941":{"count":5,"rank":3777},"1943":{"count":7,"rank":3097},"1970":{"count":5,"rank":5112},"1975":{"count":6,"rank":5148},"1978":{"count":6,"rank":5461},"1979":{"count":8,"rank":4647},"1984":{"count":5,"rank":6882},"1986":{"count":7,"rank":5683},"1987":{"count":6,"rank":6570},"1988":{"count":6,"rank":6881},"1989":{"count":8,"rank":5954},"1990":{"count":5,"rank":8869},"1991":{"count":7,"rank":6946},"1992":{"count":6,"rank":7993},"1993":{"count":6,"rank":8206},"1994":{"count":6,"rank":8327},"1995":{"count":5,"rank":9665},"1996":{"count":16,"rank":4112},"1997":{"count":6,"rank":8773},"1998":{"count":6,"rank":9124},"1999":{"count":5,"rank":10867},"2000":{"count":6,"rank":9780},"2001":{"count":5,"rank":11577},"2002":{"count":10,"rank":6818},"2003":{"count":9,"rank":7579},"2004":{"count":6,"rank":10743},"2005":{"count":8,"rank":8749},"2006":{"count":9,"rank":8428},"2007":{"count":12,"rank":6887},"2008":{"count":12,"rank":7004},"2009":{"count":10,"rank":8035},"2010":{"count":12,"rank":6917},"2011":{"count":12,"rank":6828},"2012":{"count":9,"rank":8561},"2013":{"count":13,"rank":6465},"2014":{"count":11,"rank":7324},"2015":{"count":5,"rank":13161},"2016":{"count":5,"rank":13330},"2017":{"count":8,"rank":9329},"2018":{"count":11,"rank":7400},"2019":{"count":13,"rank":6621},"2020":{"count":7,"rank":10135},"2021":{"count":12,"rank":6917},"2022":{"count":9,"rank":8676},"2023":{"count":11,"rank":7533},"2024":{"count":8,"rank":9448}}}