{"name":"Koby","gender":"M","years":{"1958":{"count":7,"rank":3438},"1959":{"count":5,"rank":4302},"1961":{"count":5,"rank":4385},"1962":{"count":11,"rank":2592},"1963":{"count":6,"rank":3843},"1965":{"count":11,"rank":2555},"1966":{"count":5,"rank":4265},"1968":{"count":7,"rank":3527},"1969":{"count":9,"rank":3205},"1970":{"count":12,"rank":2804},"1971":{"count":20,"rank":2089},"1972":{"count":12,"rank":2917},"1973":{"count":16,"rank":2454},"1974":{"count":23,"rank":1958},"1975":{"count":22,"rank":2094},"1976":{"count":22,"rank":2148},"1977":{"count":13,"rank":3125},"1978":{"count":17,"rank":2615},"1979":{"count":22,"rank":2282},"1980":{"count":20,"rank":2491},"1981":{"count":11,"rank":3742},"1982":{"count":10,"rank":4103},"1983":{"count":17,"rank":2741},"1984":{"count":20,"rank":2495},"1985":{"count":35,"rank":1747},"1986":{"count":21,"rank":2569},"1987":{"count":47,"rank":1518},"1988":{"count":51,"rank":1492},"1989":{"count":54,"rank":1527},"1990":{"count":65,"rank":1391},"1991":{"count":71,"rank":1345},"1992":{"count":66,"rank":1409},"1993":{"count":69,"rank":1401},"1994":{"count":68,"rank":1429},"1995":{"count":83,"rank":1292},"1996":{"count":116,"rank":1054},"1997":{"count":196,"rank":760},"1998":{"count":320,"rank":592},"1999":{"count":358,"rank":560},"2000":{"count":411,"rank":533},"2001":{"count":407,"rank":537},"2002":{"count":377,"rank":579},"2003":{"count":330,"rank":623},"2004":{"count":197,"rank":881},"2005":{"count":162,"rank":1037},"2006":{"count":165,"rank":1078},"2007":{"count":178,"rank":1057},"2008":{"count":180,"rank":1057},"2009":{"count":155,"rank":1171},"2010":{"count":137,"rank":1273},"2011":{"count":130,"rank":1313},"2012":{"count":105,"rank":1528},"2013":{"count":114,"rank":1452},"2014":{"count":91,"rank":1687},"2015":{"count":109,"rank":1518},"2016":{"count":99,"rank":1625},"2017":{"count":97,"rank":1637},"2018":{"count":91,"rank":1718},"2019":{"count":85,"rank":1809},"2020":{"count":101,"rank":1605},"2021":{"count":85,"rank":1829},"2022":{"count":82,"rank":1913},"2023":{"count":65,"rank":2208},"2024":{"count":73,"rank":2065}}}