{"name":"Lameka","gender":"F","years":{"1973":{"count":17,"rank":3715},"1974":{"count":15,"rank":4131},"1975":{"count":17,"rank":3856},"1976":{"count":25,"rank":2965},"1977":{"count":37,"rank":2400},"1978":{"count":46,"rank":2072},"1979":{"count":30,"rank":2893},"1980":{"count":26,"rank":3267},"1981":{"count":21,"rank":3798},"1982":{"count":28,"rank":3126},"1983":{"count":27,"rank":3101},"1984":{"count":19,"rank":4080},"1985":{"count":17,"rank":4551},"1986":{"count":18,"rank":4444},"1987":{"count":13,"rank":5773},"1988":{"count":17,"rank":4959},"1989":{"count":10,"rank":7760},"1990":{"count":11,"rank":7610},"1991":{"count":9,"rank":9000},"1992":{"count":10,"rank":8441},"1993":{"count":12,"rank":7282},"1994":{"count":7,"rank":11202},"1995":{"count":6,"rank":12615},"1996":{"count":13,"rank":6952},"1997":{"count":5,"rank":15032},"1998":{"count":6,"rank":13352},"1999":{"count":10,"rank":9190},"2000":{"count":8,"rank":11319}}}