{"name":"Mariyana","gender":"F","years":{"2002":{"count":5,"rank":17157},"2003":{"count":10,"rank":10154},"2005":{"count":9,"rank":11498},"2006":{"count":9,"rank":12056},"2007":{"count":12,"rank":9950},"2008":{"count":8,"rank":13369},"2009":{"count":12,"rank":9784},"2010":{"count":8,"rank":13042},"2011":{"count":9,"rank":11821},"2012":{"count":8,"rank":13003},"2013":{"count":8,"rank":12743},"2014":{"count":5,"rank":18261},"2015":{"count":14,"rank":8280},"2016":{"count":5,"rank":17905},"2019":{"count":7,"rank":13305},"2020":{"count":10,"rank":10009},"2023":{"count":5,"rank":16729}}}