{"name":"Messiah","gender":"M","years":{"1973":{"count":5,"rank":5610},"1974":{"count":8,"rank":4064},"1975":{"count":6,"rank":5229},"1976":{"count":6,"rank":5376},"1977":{"count":6,"rank":5601},"1978":{"count":5,"rank":6445},"1979":{"count":5,"rank":6721},"1980":{"count":10,"rank":4032},"1981":{"count":5,"rank":6930},"1984":{"count":6,"rank":6074},"1985":{"count":9,"rank":4561},"1986":{"count":5,"rank":7447},"1987":{"count":6,"rank":6669},"1988":{"count":11,"rank":4359},"1990":{"count":6,"rank":7769},"1991":{"count":12,"rank":4666},"1992":{"count":22,"rank":3076},"1993":{"count":21,"rank":3212},"1994":{"count":14,"rank":4455},"1995":{"count":30,"rank":2535},"1996":{"count":24,"rank":3078},"1997":{"count":30,"rank":2660},"1998":{"count":44,"rank":2117},"1999":{"count":94,"rank":1300},"2000":{"count":109,"rank":1232},"2001":{"count":99,"rank":1323},"2002":{"count":105,"rank":1293},"2003":{"count":118,"rank":1231},"2004":{"count":136,"rank":1156},"2005":{"count":198,"rank":905},"2006":{"count":256,"rank":800},"2007":{"count":322,"rank":718},"2008":{"count":337,"rank":700},"2009":{"count":369,"rank":665},"2010":{"count":371,"rank":649},"2011":{"count":369,"rank":635},"2012":{"count":768,"rank":389},"2013":{"count":974,"rank":334},"2014":{"count":1188,"rank":298},"2015":{"count":1516,"rank":243},"2016":{"count":1793,"rank":217},"2017":{"count":1985,"rank":198},"2018":{"count":2000,"rank":203},"2019":{"count":2035,"rank":193},"2020":{"count":2035,"rank":190},"2021":{"count":2231,"rank":172},"2022":{"count":2019,"rank":187},"2023":{"count":1914,"rank":189},"2024":{"count":1734,"rank":203}}}