{"name":"Raed","gender":"M","years":{"1975":{"count":5,"rank":6100},"1976":{"count":5,"rank":6266},"1977":{"count":6,"rank":5669},"1979":{"count":8,"rank":4738},"1980":{"count":7,"rank":5369},"1981":{"count":8,"rank":4848},"1982":{"count":5,"rank":7113},"1984":{"count":6,"rank":6132},"1986":{"count":10,"rank":4392},"1987":{"count":10,"rank":4502},"1989":{"count":7,"rank":6758},"1990":{"count":5,"rank":9166},"1991":{"count":12,"rank":4696},"1992":{"count":11,"rank":5165},"1993":{"count":10,"rank":5682},"1994":{"count":10,"rank":5777},"1995":{"count":9,"rank":6291},"1997":{"count":10,"rank":5990},"1998":{"count":7,"rank":8240},"1999":{"count":10,"rank":6395},"2000":{"count":7,"rank":8911},"2001":{"count":8,"rank":8130},"2002":{"count":7,"rank":9155},"2003":{"count":14,"rank":5483},"2004":{"count":5,"rank":12773},"2005":{"count":15,"rank":5511},"2006":{"count":7,"rank":10388},"2007":{"count":8,"rank":9550},"2008":{"count":8,"rank":9644},"2009":{"count":6,"rank":12128},"2010":{"count":10,"rank":7989},"2011":{"count":14,"rank":6173},"2012":{"count":13,"rank":6562},"2013":{"count":13,"rank":6523},"2014":{"count":17,"rank":5426},"2015":{"count":14,"rank":6231},"2016":{"count":16,"rank":5726},"2017":{"count":13,"rank":6582},"2018":{"count":17,"rank":5487},"2019":{"count":11,"rank":7508},"2020":{"count":10,"rank":7928},"2021":{"count":10,"rank":8015},"2022":{"count":23,"rank":4541},"2023":{"count":12,"rank":7185},"2024":{"count":15,"rank":6087}}}