{"name":"Rhylee","gender":"F","years":{"1993":{"count":6,"rank":13055},"1996":{"count":7,"rank":11512},"1997":{"count":8,"rank":10579},"1998":{"count":11,"rank":8453},"1999":{"count":6,"rank":14031},"2000":{"count":14,"rank":7493},"2001":{"count":19,"rank":6019},"2002":{"count":32,"rank":4052},"2003":{"count":29,"rank":4508},"2004":{"count":38,"rank":3802},"2005":{"count":40,"rank":3714},"2006":{"count":48,"rank":3407},"2007":{"count":51,"rank":3321},"2008":{"count":73,"rank":2574},"2009":{"count":90,"rank":2203},"2010":{"count":108,"rank":1882},"2011":{"count":95,"rank":2055},"2012":{"count":132,"rank":1637},"2013":{"count":132,"rank":1629},"2014":{"count":90,"rank":2135},"2015":{"count":122,"rank":1727},"2016":{"count":128,"rank":1678},"2017":{"count":108,"rank":1887},"2018":{"count":196,"rank":1209},"2019":{"count":232,"rank":1081},"2020":{"count":165,"rank":1340},"2021":{"count":134,"rank":1574},"2022":{"count":123,"rank":1703},"2023":{"count":84,"rank":2240},"2024":{"count":97,"rank":2022}}}