{"name":"Shloma","gender":"M","years":{"1974":{"count":6,"rank":5145},"1977":{"count":7,"rank":5039},"1979":{"count":5,"rank":6937},"1982":{"count":6,"rank":6284},"1988":{"count":5,"rank":8324},"1994":{"count":7,"rank":7634},"1995":{"count":7,"rank":7680},"1996":{"count":10,"rank":5909},"1997":{"count":9,"rank":6533},"1998":{"count":6,"rank":9472},"1999":{"count":10,"rank":6440},"2000":{"count":10,"rank":6753},"2001":{"count":7,"rank":9086},"2002":{"count":14,"rank":5354},"2003":{"count":10,"rank":7163},"2004":{"count":18,"rank":4762},"2005":{"count":15,"rank":5536},"2006":{"count":10,"rank":7907},"2007":{"count":18,"rank":5177},"2008":{"count":15,"rank":6017},"2009":{"count":15,"rank":6041},"2010":{"count":13,"rank":6649},"2011":{"count":10,"rank":7970},"2012":{"count":15,"rank":5943},"2013":{"count":6,"rank":11938},"2014":{"count":17,"rank":5446},"2015":{"count":26,"rank":4060},"2016":{"count":13,"rank":6667},"2017":{"count":18,"rank":5267},"2018":{"count":30,"rank":3687},"2019":{"count":29,"rank":3785},"2020":{"count":8,"rank":9420},"2021":{"count":25,"rank":4215},"2022":{"count":23,"rank":4548},"2023":{"count":28,"rank":3980},"2024":{"count":26,"rank":4157}}}