{"name":"Sostenes","gender":"M","years":{"1919":{"count":5,"rank":4716},"1924":{"count":9,"rank":3228},"1927":{"count":5,"rank":4716},"1929":{"count":10,"rank":2741},"1933":{"count":6,"rank":3592},"1934":{"count":6,"rank":3629},"1936":{"count":6,"rank":3502},"1937":{"count":5,"rank":3954},"1941":{"count":8,"rank":2850},"1944":{"count":6,"rank":3392},"1953":{"count":7,"rank":3393},"1958":{"count":5,"rank":4437},"1962":{"count":7,"rank":3590},"1981":{"count":6,"rank":6150},"1986":{"count":6,"rank":6622},"1987":{"count":5,"rank":7985},"1992":{"count":5,"rank":9623},"1993":{"count":5,"rank":9955},"1996":{"count":5,"rank":10334},"1997":{"count":5,"rank":10598}}}