{"name":"Tamisha","gender":"F","years":{"1968":{"count":6,"rank":6917},"1969":{"count":10,"rank":5016},"1970":{"count":12,"rank":4736},"1971":{"count":32,"rank":2419},"1972":{"count":52,"rank":1719},"1973":{"count":60,"rank":1565},"1974":{"count":122,"rank":997},"1975":{"count":88,"rank":1276},"1976":{"count":105,"rank":1133},"1977":{"count":112,"rank":1138},"1978":{"count":115,"rank":1132},"1979":{"count":89,"rank":1392},"1980":{"count":115,"rank":1174},"1981":{"count":85,"rank":1444},"1982":{"count":115,"rank":1191},"1983":{"count":104,"rank":1228},"1984":{"count":83,"rank":1410},"1985":{"count":74,"rank":1620},"1986":{"count":80,"rank":1537},"1987":{"count":73,"rank":1676},"1988":{"count":73,"rank":1755},"1989":{"count":80,"rank":1715},"1990":{"count":58,"rank":2229},"1991":{"count":65,"rank":2091},"1992":{"count":59,"rank":2272},"1993":{"count":42,"rank":2876},"1994":{"count":50,"rank":2535},"1995":{"count":41,"rank":2925},"1996":{"count":33,"rank":3497},"1997":{"count":32,"rank":3619},"1998":{"count":15,"rank":6688},"1999":{"count":22,"rank":5021},"2000":{"count":17,"rank":6455},"2001":{"count":14,"rank":7682},"2002":{"count":11,"rank":9420},"2003":{"count":9,"rank":11237},"2004":{"count":14,"rank":8206},"2005":{"count":6,"rank":16234},"2006":{"count":8,"rank":13485},"2007":{"count":7,"rank":15313}}}