{"name":"Timberlyn","gender":"F","years":{"1995":{"count":6,"rank":13275},"1997":{"count":6,"rank":13603},"1998":{"count":5,"rank":16416},"1999":{"count":5,"rank":16744},"2002":{"count":5,"rank":17901},"2003":{"count":5,"rank":18212},"2004":{"count":6,"rank":15947},"2005":{"count":6,"rank":16293},"2006":{"count":5,"rank":19841},"2007":{"count":5,"rank":20328},"2008":{"count":5,"rank":20235},"2009":{"count":7,"rank":15114},"2011":{"count":5,"rank":19371},"2013":{"count":8,"rank":13054},"2014":{"count":6,"rank":16356},"2015":{"count":10,"rank":10802},"2016":{"count":7,"rank":14211},"2017":{"count":14,"rank":8258},"2018":{"count":10,"rank":10491},"2019":{"count":10,"rank":10415},"2020":{"count":6,"rank":14941},"2021":{"count":12,"rank":8924},"2022":{"count":10,"rank":10325},"2023":{"count":9,"rank":11081},"2024":{"count":6,"rank":15047}}}