{"name":"Travis","gender":"M","years":{"1880":{"count":12,"rank":564},"1882":{"count":10,"rank":649},"1883":{"count":9,"rank":673},"1884":{"count":10,"rank":657},"1885":{"count":11,"rank":601},"1886":{"count":11,"rank":599},"1888":{"count":6,"rank":1021},"1889":{"count":7,"rank":872},"1890":{"count":9,"rank":734},"1891":{"count":9,"rank":697},"1892":{"count":13,"rank":594},"1893":{"count":8,"rank":832},"1894":{"count":8,"rank":850},"1895":{"count":10,"rank":735},"1896":{"count":10,"rank":775},"1897":{"count":12,"rank":646},"1898":{"count":7,"rank":992},"1899":{"count":11,"rank":658},"1900":{"count":27,"rank":443},"1901":{"count":6,"rank":1051},"1902":{"count":16,"rank":553},"1903":{"count":10,"rank":779},"1904":{"count":19,"rank":511},"1905":{"count":21,"rank":506},"1906":{"count":17,"rank":588},"1907":{"count":21,"rank":537},"1908":{"count":25,"rank":512},"1909":{"count":32,"rank":452},"1910":{"count":31,"rank":511},"1911":{"count":40,"rank":468},"1912":{"count":77,"rank":449},"1913":{"count":109,"rank":414},"1914":{"count":150,"rank":389},"1915":{"count":160,"rank":427},"1916":{"count":189,"rank":405},"1917":{"count":205,"rank":395},"1918":{"count":244,"rank":382},"1919":{"count":232,"rank":383},"1920":{"count":240,"rank":386},"1921":{"count":246,"rank":386},"1922":{"count":262,"rank":373},"1923":{"count":237,"rank":386},"1924":{"count":246,"rank":383},"1925":{"count":241,"rank":386},"1926":{"count":217,"rank":406},"1927":{"count":256,"rank":365},"1928":{"count":243,"rank":375},"1929":{"count":273,"rank":338},"1930":{"count":254,"rank":361},"1931":{"count":286,"rank":325},"1932":{"count":282,"rank":329},"1933":{"count":295,"rank":313},"1934":{"count":364,"rank":282},"1935":{"count":345,"rank":294},"1936":{"count":335,"rank":295},"1937":{"count":320,"rank":302},"1938":{"count":354,"rank":291},"1939":{"count":353,"rank":296},"1940":{"count":355,"rank":295},"1941":{"count":350,"rank":310},"1942":{"count":359,"rank":320},"1943":{"count":315,"rank":348},"1944":{"count":334,"rank":331},"1945":{"count":307,"rank":344},"1946":{"count":406,"rank":320},"1947":{"count":408,"rank":338},"1948":{"count":373,"rank":348},"1949":{"count":373,"rank":350},"1950":{"count":383,"rank":345},"1951":{"count":374,"rank":355},"1952":{"count":366,"rank":356},"1953":{"count":383,"rank":355},"1954":{"count":360,"rank":371},"1955":{"count":356,"rank":381},"1956":{"count":384,"rank":385},"1957":{"count":353,"rank":416},"1958":{"count":434,"rank":372},"1959":{"count":505,"rank":346},"1960":{"count":549,"rank":330},"1961":{"count":585,"rank":324},"1962":{"count":653,"rank":303},"1963":{"count":886,"rank":258},"1964":{"count":1024,"rank":236},"1965":{"count":1077,"rank":222},"1966":{"count":1299,"rank":189},"1967":{"count":1602,"rank":166},"1968":{"count":2063,"rank":141},"1969":{"count":2862,"rank":114},"1970":{"count":4323,"rank":69},"1971":{"count":5015,"rank":61},"1972":{"count":5138,"rank":57},"1973":{"count":5867,"rank":53},"1974":{"count":5702,"rank":54},"1975":{"count":5960,"rank":51},"1976":{"count":6833,"rank":46},"1977":{"count":7277,"rank":44},"1978":{"count":6955,"rank":46},"1979":{"count":11037,"rank":36},"1980":{"count":10765,"rank":37},"1981":{"count":10109,"rank":40},"1982":{"count":10415,"rank":39},"1983":{"count":10480,"rank":41},"1984":{"count":10240,"rank":42},"1985":{"count":9094,"rank":46},"1986":{"count":8480,"rank":49},"1987":{"count":10397,"rank":42},"1988":{"count":11421,"rank":41},"1989":{"count":11528,"rank":41},"1990":{"count":11460,"rank":42},"1991":{"count":10134,"rank":44},"1992":{"count":8895,"rank":48},"1993":{"count":7942,"rank":50},"1994":{"count":6800,"rank":53},"1995":{"count":5602,"rank":66},"1996":{"count":5159,"rank":73},"1997":{"count":4684,"rank":81},"1998":{"count":3924,"rank":98},"1999":{"count":3608,"rank":102},"2000":{"count":3289,"rank":115},"2001":{"count":2943,"rank":134},"2002":{"count":2702,"rank":144},"2003":{"count":2541,"rank":159},"2004":{"count":2461,"rank":166},"2005":{"count":2368,"rank":175},"2006":{"count":2599,"rank":162},"2007":{"count":2403,"rank":170},"2008":{"count":2232,"rank":177},"2009":{"count":2198,"rank":177},"2010":{"count":2126,"rank":178},"2011":{"count":1943,"rank":190},"2012":{"count":1758,"rank":212},"2013":{"count":1585,"rank":232},"2014":{"count":1491,"rank":253},"2015":{"count":1404,"rank":257},"2016":{"count":1314,"rank":276},"2017":{"count":1167,"rank":303},"2018":{"count":1077,"rank":314},"2019":{"count":1031,"rank":322},"2020":{"count":964,"rank":338},"2021":{"count":848,"rank":381},"2022":{"count":848,"rank":382},"2023":{"count":846,"rank":379},"2024":{"count":914,"rank":361}}}