{"name":"Tyresse","gender":"M","years":{"1979":{"count":6,"rank":6017},"1983":{"count":5,"rank":7281},"1988":{"count":7,"rank":6382},"1991":{"count":6,"rank":8189},"1998":{"count":11,"rank":5823},"1999":{"count":62,"rank":1708},"2000":{"count":23,"rank":3629},"2001":{"count":19,"rank":4289},"2002":{"count":20,"rank":4180},"2003":{"count":20,"rank":4267},"2004":{"count":8,"rank":8866},"2005":{"count":7,"rank":10083},"2006":{"count":16,"rank":5505},"2007":{"count":10,"rank":8127},"2008":{"count":12,"rank":7156},"2009":{"count":10,"rank":8266},"2010":{"count":7,"rank":10680},"2011":{"count":8,"rank":9536},"2012":{"count":6,"rank":12178},"2014":{"count":5,"rank":13921},"2021":{"count":5,"rank":13917}}}