{"name":"Violeta","gender":"F","years":{"1918":{"count":5,"rank":5550},"1920":{"count":5,"rank":5722},"1921":{"count":5,"rank":5827},"1923":{"count":7,"rank":4359},"1925":{"count":9,"rank":3652},"1926":{"count":10,"rank":3258},"1927":{"count":5,"rank":5575},"1928":{"count":5,"rank":5398},"1929":{"count":10,"rank":3129},"1931":{"count":9,"rank":3214},"1934":{"count":5,"rank":4945},"1935":{"count":7,"rank":3728},"1936":{"count":12,"rank":2516},"1938":{"count":6,"rank":4325},"1943":{"count":5,"rank":5342},"1944":{"count":5,"rank":5217},"1945":{"count":7,"rank":4011},"1946":{"count":8,"rank":3984},"1947":{"count":5,"rank":6083},"1948":{"count":6,"rank":5222},"1949":{"count":11,"rank":3388},"1950":{"count":12,"rank":3225},"1951":{"count":16,"rank":2689},"1952":{"count":9,"rank":4112},"1953":{"count":12,"rank":3471},"1954":{"count":8,"rank":4640},"1955":{"count":14,"rank":3217},"1956":{"count":8,"rank":4823},"1957":{"count":8,"rank":4902},"1958":{"count":14,"rank":3375},"1959":{"count":13,"rank":3614},"1960":{"count":12,"rank":3914},"1961":{"count":17,"rank":3188},"1962":{"count":22,"rank":2666},"1963":{"count":20,"rank":2862},"1964":{"count":22,"rank":2748},"1965":{"count":25,"rank":2462},"1966":{"count":22,"rank":2666},"1967":{"count":23,"rank":2629},"1968":{"count":26,"rank":2480},"1969":{"count":28,"rank":2515},"1970":{"count":21,"rank":3201},"1971":{"count":44,"rank":1965},"1972":{"count":67,"rank":1455},"1973":{"count":62,"rank":1526},"1974":{"count":60,"rank":1597},"1975":{"count":47,"rank":1933},"1976":{"count":55,"rank":1746},"1977":{"count":59,"rank":1760},"1978":{"count":83,"rank":1411},"1979":{"count":82,"rank":1471},"1980":{"count":106,"rank":1244},"1981":{"count":93,"rank":1353},"1982":{"count":94,"rank":1336},"1983":{"count":88,"rank":1371},"1984":{"count":83,"rank":1412},"1985":{"count":160,"rank":968},"1986":{"count":91,"rank":1419},"1987":{"count":69,"rank":1746},"1988":{"count":74,"rank":1737},"1989":{"count":62,"rank":2052},"1990":{"count":102,"rank":1522},"1991":{"count":93,"rank":1627},"1992":{"count":54,"rank":2429},"1993":{"count":96,"rank":1601},"1994":{"count":88,"rank":1706},"1995":{"count":73,"rank":1918},"1996":{"count":55,"rank":2397},"1997":{"count":53,"rank":2480},"1998":{"count":74,"rank":2025},"1999":{"count":56,"rank":2565},"2000":{"count":69,"rank":2276},"2001":{"count":75,"rank":2191},"2002":{"count":124,"rank":1534},"2003":{"count":115,"rank":1673},"2004":{"count":101,"rank":1882},"2005":{"count":119,"rank":1678},"2006":{"count":166,"rank":1379},"2007":{"count":185,"rank":1321},"2008":{"count":139,"rank":1634},"2009":{"count":215,"rank":1172},"2010":{"count":250,"rank":1007},"2011":{"count":215,"rank":1143},"2012":{"count":231,"rank":1078},"2013":{"count":207,"rank":1163},"2014":{"count":191,"rank":1267},"2015":{"count":221,"rank":1151},"2016":{"count":246,"rank":1063},"2017":{"count":257,"rank":1013},"2018":{"count":273,"rank":969},"2019":{"count":299,"rank":892},"2020":{"count":298,"rank":892},"2021":{"count":304,"rank":889},"2022":{"count":391,"rank":741},"2023":{"count":450,"rank":655},"2024":{"count":413,"rank":686}}}