{"name":"Zabdiel","gender":"M","years":{"1986":{"count":5,"rank":7815},"1990":{"count":6,"rank":8103},"1991":{"count":6,"rank":8222},"1992":{"count":7,"rank":7409},"1993":{"count":5,"rank":10149},"1994":{"count":5,"rank":10225},"1995":{"count":7,"rank":7784},"1996":{"count":7,"rank":7956},"1997":{"count":6,"rank":9247},"1998":{"count":7,"rank":8461},"1999":{"count":14,"rank":5025},"2000":{"count":7,"rank":9095},"2001":{"count":14,"rank":5388},"2002":{"count":18,"rank":4495},"2003":{"count":19,"rank":4419},"2004":{"count":16,"rank":5239},"2005":{"count":20,"rank":4461},"2006":{"count":23,"rank":4219},"2007":{"count":21,"rank":4634},"2008":{"count":30,"rank":3644},"2009":{"count":26,"rank":4031},"2010":{"count":23,"rank":4363},"2011":{"count":25,"rank":4103},"2012":{"count":18,"rank":5247},"2013":{"count":16,"rank":5653},"2014":{"count":15,"rank":5989},"2015":{"count":33,"rank":3428},"2016":{"count":112,"rank":1519},"2017":{"count":101,"rank":1604},"2018":{"count":84,"rank":1822},"2019":{"count":76,"rank":1952},"2020":{"count":61,"rank":2258},"2021":{"count":68,"rank":2132},"2022":{"count":205,"rank":1072},"2023":{"count":174,"rank":1181},"2024":{"count":119,"rank":1504}}}