{"name":"Zakia","gender":"F","years":{"1971":{"count":9,"rank":6006},"1972":{"count":13,"rank":4521},"1973":{"count":16,"rank":3969},"1974":{"count":20,"rank":3425},"1975":{"count":88,"rank":1278},"1976":{"count":51,"rank":1839},"1977":{"count":41,"rank":2256},"1978":{"count":21,"rank":3636},"1979":{"count":37,"rank":2524},"1980":{"count":42,"rank":2341},"1981":{"count":31,"rank":2927},"1982":{"count":28,"rank":3170},"1983":{"count":26,"rank":3240},"1984":{"count":23,"rank":3612},"1985":{"count":22,"rank":3851},"1986":{"count":24,"rank":3644},"1987":{"count":27,"rank":3424},"1988":{"count":28,"rank":3480},"1989":{"count":46,"rank":2526},"1990":{"count":33,"rank":3361},"1991":{"count":40,"rank":2934},"1992":{"count":43,"rank":2828},"1993":{"count":41,"rank":2937},"1994":{"count":36,"rank":3232},"1995":{"count":54,"rank":2420},"1996":{"count":42,"rank":2900},"1997":{"count":39,"rank":3104},"1998":{"count":63,"rank":2278},"1999":{"count":50,"rank":2781},"2000":{"count":44,"rank":3167},"2001":{"count":45,"rank":3139},"2002":{"count":46,"rank":3144},"2003":{"count":48,"rank":3129},"2004":{"count":44,"rank":3442},"2005":{"count":49,"rank":3209},"2006":{"count":40,"rank":3851},"2007":{"count":49,"rank":3425},"2008":{"count":28,"rank":5275},"2009":{"count":31,"rank":4800},"2010":{"count":27,"rank":5241},"2011":{"count":19,"rank":6843},"2012":{"count":26,"rank":5394},"2013":{"count":17,"rank":7364},"2014":{"count":22,"rank":5985},"2015":{"count":17,"rank":7259},"2016":{"count":18,"rank":6896},"2017":{"count":21,"rank":6035},"2018":{"count":13,"rank":8599},"2019":{"count":12,"rank":9095},"2020":{"count":20,"rank":6071},"2021":{"count":8,"rank":12168},"2022":{"count":14,"rank":8017},"2023":{"count":13,"rank":8465},"2024":{"count":9,"rank":11049}}}