{"name":"Zarah","gender":"F","years":{"1968":{"count":5,"rank":8195},"1969":{"count":5,"rank":8700},"1971":{"count":5,"rank":9643},"1977":{"count":11,"rank":5886},"1978":{"count":8,"rank":7646},"1979":{"count":11,"rank":6187},"1980":{"count":11,"rank":6318},"1981":{"count":12,"rank":5884},"1982":{"count":12,"rank":5906},"1983":{"count":6,"rank":10272},"1984":{"count":8,"rank":8150},"1985":{"count":14,"rank":5346},"1986":{"count":14,"rank":5458},"1987":{"count":10,"rank":7352},"1988":{"count":16,"rank":5321},"1989":{"count":14,"rank":6158},"1990":{"count":17,"rank":5548},"1991":{"count":14,"rank":6584},"1992":{"count":16,"rank":6006},"1993":{"count":23,"rank":4522},"1994":{"count":21,"rank":4843},"1995":{"count":18,"rank":5438},"1996":{"count":21,"rank":4881},"1997":{"count":19,"rank":5413},"1998":{"count":19,"rank":5581},"1999":{"count":36,"rank":3506},"2000":{"count":35,"rank":3737},"2001":{"count":39,"rank":3485},"2002":{"count":34,"rank":3887},"2003":{"count":44,"rank":3346},"2004":{"count":31,"rank":4490},"2005":{"count":40,"rank":3726},"2006":{"count":69,"rank":2630},"2007":{"count":60,"rank":2991},"2008":{"count":73,"rank":2583},"2009":{"count":80,"rank":2424},"2010":{"count":94,"rank":2117},"2011":{"count":96,"rank":2042},"2012":{"count":99,"rank":1982},"2013":{"count":81,"rank":2304},"2014":{"count":92,"rank":2111},"2015":{"count":122,"rank":1730},"2016":{"count":119,"rank":1756},"2017":{"count":147,"rank":1512},"2018":{"count":116,"rank":1773},"2019":{"count":141,"rank":1539},"2020":{"count":141,"rank":1515},"2021":{"count":168,"rank":1333},"2022":{"count":198,"rank":1223},"2023":{"count":157,"rank":1424},"2024":{"count":162,"rank":1391}}}